setup.cfg
setup.py
conf/grinder.conf
grinder/__init__.py
grinder/core.py
grinder/environment.py
grinder/repository.py
grinder/seasoning.py
grinder.egg-info/PKG-INFO
grinder.egg-info/SOURCES.txt
grinder.egg-info/dependency_links.txt
grinder.egg-info/requires.txt
grinder.egg-info/top_level.txt
scripts/grinder