Metadata-Version: 1.1
Name: grinder
Version: 0.1
Summary: Dynamic environment deployment tool for SaltStack
Home-page: https://github.com/frozenfoxx/grinder
Author: FrozenFOXX
Author-email: siliconfoxx@gmail.com
License: UNKNOWN
Download-URL: https://github.com/frozenfoxx/grinder/archive/0.1.tar.gz
Keywords: salt,devops,deployment,pillar
Platform: UNKNOWN
